MANIFEST.in
cmd.sh
setup.py
test.py
src/Bitvec.cpp
src/Bitvec.h
src/City.cpp
src/City.h
src/MurmurHash3.cpp
src/MurmurHash3.h
src/Platform.cpp
src/Platform.h
src/Random.cpp
src/Random.h
src/Types.cpp
src/Types.h
src/md5.cpp
src/sha1.cpp
src/sha1.h
src/xhashes.cpp
src/xhashes.h
src/xwCHash.cpp
src/xwCHash.pyx
xwHash.egg-info/PKG-INFO
xwHash.egg-info/SOURCES.txt
xwHash.egg-info/dependency_links.txt
xwHash.egg-info/top_level.txt