Metadata-Version: 1.0
Name: xwHash
Version: 0.0.2
Summary: hashes from c++ libary
Home-page: UNKNOWN
Author: vicky xiao
Author-email: xwq20080101@gmail.com
License: UNKNOWN
Platform: UNKNOWN
